{
  "type": "File",
  "start": 0,
  "end": 1219,
  "loc": {
    "start": {
      "line": 1,
      "column": 0
    },
    "end": {
      "line": 29,
      "column": 25
    }
  },
  "program": {
    "type": "Program",
    "start": 0,
    "end": 1219,
    "loc": {
      "start": {
        "line": 1,
        "column": 0
      },
      "end": {
        "line": 29,
        "column": 25
      }
    },
    "sourceType": "module",
    "body": [
      {
        "type": "Identifier",
        "start": 0,
        "end": 1191,
        "loc": {
          "start": {
            "line": 1,
            "column": 0
          },
          "end": {
            "line": 26,
            "column": 1
          }
        },
        "id": {
          "type": "Identifier",
          "start": 6,
          "end": 15,
          "loc": {
            "start": {
              "line": 1,
              "column": 6
            },
            "end": {
              "line": 1,
              "column": 15
            },
            "identifierName": "Constants"
          },
          "name": "Constants"
        },
        "superClass": null,
        "body": {
          "type": "ClassBody",
          "start": 16,
          "end": 1191,
          "loc": {
            "start": {
              "line": 1,
              "column": 16
            },
            "end": {
              "line": 26,
              "column": 1
            }
          },
          "body": [
            {
              "type": "ClassMethod",
              "start": 24,
              "end": 118,
              "loc": {
                "start": {
                  "line": 2,
                  "column": 6
                },
                "end": {
                  "line": 4,
                  "column": 7
                }
              },
              "static": true,
              "computed": false,
              "key": {
                "type": "Identifier",
                "start": 35,
                "end": 42,
                "loc": {
                  "start": {
                    "line": 2,
                    "column": 17
                  },
                  "end": {
                    "line": 2,
                    "column": 24
                  },
                  "identifierName": "FontPdf"
                },
                "name": "FontPdf"
              },
              "kind": "get",
              "id": null,
              "generator": false,
              "expression": false,
              "async": false,
              "params": [],
              "body": {
                "type": "BlockStatement",
                "start": 45,
                "end": 118,
                "loc": {
                  "start": {
                    "line": 2,
                    "column": 27
                  },
                  "end": {
                    "line": 4,
                    "column": 7
                  }
                },
                "body": [
                  {
                    "type": "ReturnStatement",
                    "start": 55,
                    "end": 110,
                    "loc": {
                      "start": {
                        "line": 3,
                        "column": 8
                      },
                      "end": {
                        "line": 3,
                        "column": 63
                      }
                    },
                    "argument": {
                      "type": "StringLiteral",
                      "start": 62,
                      "end": 109,
                      "loc": {
                        "start": {
                          "line": 3,
                          "column": 15
                        },
                        "end": {
                          "line": 3,
                          "column": 62
                        }
                      },
                      "extra": {
                        "rawValue": "https://fonts.cdnfonts.com/css/sst-typewriter",
                        "raw": "'https://fonts.cdnfonts.com/css/sst-typewriter'"
                      },
                      "value": "https://fonts.cdnfonts.com/css/sst-typewriter"
                    }
                  }
                ],
                "directives": []
              }
            },
            {
              "type": "ClassMethod",
              "start": 125,
              "end": 269,
              "loc": {
                "start": {
                  "line": 5,
                  "column": 6
                },
                "end": {
                  "line": 7,
                  "column": 7
                }
              },
              "static": true,
              "computed": false,
              "key": {
                "type": "Identifier",
                "start": 136,
                "end": 150,
                "loc": {
                  "start": {
                    "line": 5,
                    "column": 17
                  },
                  "end": {
                    "line": 5,
                    "column": 31
                  },
                  "identifierName": "LogoFedrannPdf"
                },
                "name": "LogoFedrannPdf"
              },
              "kind": "get",
              "id": null,
              "generator": false,
              "expression": false,
              "async": false,
              "params": [],
              "body": {
                "type": "BlockStatement",
                "start": 153,
                "end": 269,
                "loc": {
                  "start": {
                    "line": 5,
                    "column": 34
                  },
                  "end": {
                    "line": 7,
                    "column": 7
                  }
                },
                "body": [
                  {
                    "type": "ReturnStatement",
                    "start": 163,
                    "end": 261,
                    "loc": {
                      "start": {
                        "line": 6,
                        "column": 8
                      },
                      "end": {
                        "line": 6,
                        "column": 106
                      }
                    },
                    "argument": {
                      "type": "StringLiteral",
                      "start": 170,
                      "end": 260,
                      "loc": {
                        "start": {
                          "line": 6,
                          "column": 15
                        },
                        "end": {
                          "line": 6,
                          "column": 105
                        }
                      },
                      "extra": {
                        "rawValue": "https://cdn.discordapp.com/attachments/973237631959855234/1118854023995465758/Logo_1.png",
                        "raw": "\"https://cdn.discordapp.com/attachments/973237631959855234/1118854023995465758/Logo_1.png\""
                      },
                      "value": "https://cdn.discordapp.com/attachments/973237631959855234/1118854023995465758/Logo_1.png"
                    }
                  }
                ],
                "directives": []
              }
            },
            {
              "type": "ClassMethod",
              "start": 276,
              "end": 422,
              "loc": {
                "start": {
                  "line": 8,
                  "column": 6
                },
                "end": {
                  "line": 10,
                  "column": 7
                }
              },
              "static": true,
              "computed": false,
              "key": {
                "type": "Identifier",
                "start": 287,
                "end": 299,
                "loc": {
                  "start": {
                    "line": 8,
                    "column": 17
                  },
                  "end": {
                    "line": 8,
                    "column": 29
                  },
                  "identifierName": "LecturePhoto"
                },
                "name": "LecturePhoto"
              },
              "kind": "get",
              "id": null,
              "generator": false,
              "expression": false,
              "async": false,
              "params": [],
              "body": {
                "type": "BlockStatement",
                "start": 302,
                "end": 422,
                "loc": {
                  "start": {
                    "line": 8,
                    "column": 32
                  },
                  "end": {
                    "line": 10,
                    "column": 7
                  }
                },
                "body": [
                  {
                    "type": "ReturnStatement",
                    "start": 312,
                    "end": 414,
                    "loc": {
                      "start": {
                        "line": 9,
                        "column": 8
                      },
                      "end": {
                        "line": 9,
                        "column": 110
                      }
                    },
                    "argument": {
                      "type": "StringLiteral",
                      "start": 319,
                      "end": 413,
                      "loc": {
                        "start": {
                          "line": 9,
                          "column": 15
                        },
                        "end": {
                          "line": 9,
                          "column": 109
                        }
                      },
                      "extra": {
                        "rawValue": "https://cdn.discordapp.com/attachments/973237631959855234/1121098716846227526/DSC05369_1.png",
                        "raw": "\"https://cdn.discordapp.com/attachments/973237631959855234/1121098716846227526/DSC05369_1.png\""
                      },
                      "value": "https://cdn.discordapp.com/attachments/973237631959855234/1121098716846227526/DSC05369_1.png"
                    }
                  }
                ],
                "directives": []
              }
            },
            {
              "type": "ClassMethod",
              "start": 429,
              "end": 580,
              "loc": {
                "start": {
                  "line": 11,
                  "column": 6
                },
                "end": {
                  "line": 13,
                  "column": 7
                }
              },
              "static": true,
              "computed": false,
              "key": {
                "type": "Identifier",
                "start": 440,
                "end": 449,
                "loc": {
                  "start": {
                    "line": 11,
                    "column": 17
                  },
                  "end": {
                    "line": 11,
                    "column": 26
                  },
                  "identifierName": "LockPhoto"
                },
                "name": "LockPhoto"
              },
              "kind": "get",
              "id": null,
              "generator": false,
              "expression": false,
              "async": false,
              "params": [],
              "body": {
                "type": "BlockStatement",
                "start": 452,
                "end": 580,
                "loc": {
                  "start": {
                    "line": 11,
                    "column": 29
                  },
                  "end": {
                    "line": 13,
                    "column": 7
                  }
                },
                "body": [
                  {
                    "type": "ReturnStatement",
                    "start": 462,
                    "end": 572,
                    "loc": {
                      "start": {
                        "line": 12,
                        "column": 8
                      },
                      "end": {
                        "line": 12,
                        "column": 118
                      }
                    },
                    "argument": {
                      "type": "StringLiteral",
                      "start": 469,
                      "end": 571,
                      "loc": {
                        "start": {
                          "line": 12,
                          "column": 15
                        },
                        "end": {
                          "line": 12,
                          "column": 117
                        }
                      },
                      "extra": {
                        "rawValue": "https://cdn.discordapp.com/attachments/973237631959855234/1121430756191899808/cadeado_complexo_2.png",
                        "raw": "\"https://cdn.discordapp.com/attachments/973237631959855234/1121430756191899808/cadeado_complexo_2.png\""
                      },
                      "value": "https://cdn.discordapp.com/attachments/973237631959855234/1121430756191899808/cadeado_complexo_2.png"
                    }
                  }
                ],
                "directives": []
              }
            },
            {
              "type": "ClassMethod",
              "start": 587,
              "end": 728,
              "loc": {
                "start": {
                  "line": 14,
                  "column": 6
                },
                "end": {
                  "line": 16,
                  "column": 7
                }
              },
              "static": true,
              "computed": false,
              "key": {
                "type": "Identifier",
                "start": 598,
                "end": 609,
                "loc": {
                  "start": {
                    "line": 14,
                    "column": 17
                  },
                  "end": {
                    "line": 14,
                    "column": 28
                  },
                  "identifierName": "TicketPhoto"
                },
                "name": "TicketPhoto"
              },
              "kind": "get",
              "id": null,
              "generator": false,
              "expression": false,
              "async": false,
              "params": [],
              "body": {
                "type": "BlockStatement",
                "start": 612,
                "end": 728,
                "loc": {
                  "start": {
                    "line": 14,
                    "column": 31
                  },
                  "end": {
                    "line": 16,
                    "column": 7
                  }
                },
                "body": [
                  {
                    "type": "ReturnStatement",
                    "start": 622,
                    "end": 720,
                    "loc": {
                      "start": {
                        "line": 15,
                        "column": 8
                      },
                      "end": {
                        "line": 15,
                        "column": 106
                      }
                    },
                    "argument": {
                      "type": "StringLiteral",
                      "start": 629,
                      "end": 719,
                      "loc": {
                        "start": {
                          "line": 15,
                          "column": 15
                        },
                        "end": {
                          "line": 15,
                          "column": 105
                        }
                      },
                      "extra": {
                        "rawValue": "https://cdn.discordapp.com/attachments/973237631959855234/1121430325575286904/ticket.png",
                        "raw": "\"https://cdn.discordapp.com/attachments/973237631959855234/1121430325575286904/ticket.png\""
                      },
                      "value": "https://cdn.discordapp.com/attachments/973237631959855234/1121430325575286904/ticket.png"
                    }
                  }
                ],
                "directives": []
              }
            },
            {
              "type": "ClassMethod",
              "start": 735,
              "end": 880,
              "loc": {
                "start": {
                  "line": 17,
                  "column": 6
                },
                "end": {
                  "line": 19,
                  "column": 7
                }
              },
              "static": true,
              "computed": false,
              "key": {
                "type": "Identifier",
                "start": 746,
                "end": 756,
                "loc": {
                  "start": {
                    "line": 17,
                    "column": 17
                  },
                  "end": {
                    "line": 17,
                    "column": 27
                  },
                  "identifierName": "ClockPhoto"
                },
                "name": "ClockPhoto"
              },
              "kind": "get",
              "id": null,
              "generator": false,
              "expression": false,
              "async": false,
              "params": [],
              "body": {
                "type": "BlockStatement",
                "start": 759,
                "end": 880,
                "loc": {
                  "start": {
                    "line": 17,
                    "column": 30
                  },
                  "end": {
                    "line": 19,
                    "column": 7
                  }
                },
                "body": [
                  {
                    "type": "ReturnStatement",
                    "start": 769,
                    "end": 872,
                    "loc": {
                      "start": {
                        "line": 18,
                        "column": 8
                      },
                      "end": {
                        "line": 18,
                        "column": 111
                      }
                    },
                    "argument": {
                      "type": "StringLiteral",
                      "start": 776,
                      "end": 871,
                      "loc": {
                        "start": {
                          "line": 18,
                          "column": 15
                        },
                        "end": {
                          "line": 18,
                          "column": 110
                        }
                      },
                      "extra": {
                        "rawValue": "https://cdn.discordapp.com/attachments/973237631959855234/1121102237108813864/Rectangle_3.png",
                        "raw": "\"https://cdn.discordapp.com/attachments/973237631959855234/1121102237108813864/Rectangle_3.png\""
                      },
                      "value": "https://cdn.discordapp.com/attachments/973237631959855234/1121102237108813864/Rectangle_3.png"
                    }
                  }
                ],
                "directives": []
              }
            },
            {
              "type": "ClassMethod",
              "start": 887,
              "end": 1033,
              "loc": {
                "start": {
                  "line": 20,
                  "column": 6
                },
                "end": {
                  "line": 22,
                  "column": 7
                }
              },
              "static": true,
              "computed": false,
              "key": {
                "type": "Identifier",
                "start": 898,
                "end": 914,
                "loc": {
                  "start": {
                    "line": 20,
                    "column": 17
                  },
                  "end": {
                    "line": 20,
                    "column": 33
                  },
                  "identifierName": "FontConfirmEmail"
                },
                "name": "FontConfirmEmail"
              },
              "kind": "get",
              "id": null,
              "generator": false,
              "expression": false,
              "async": false,
              "params": [],
              "body": {
                "type": "BlockStatement",
                "start": 917,
                "end": 1033,
                "loc": {
                  "start": {
                    "line": 20,
                    "column": 36
                  },
                  "end": {
                    "line": 22,
                    "column": 7
                  }
                },
                "body": [
                  {
                    "type": "ReturnStatement",
                    "start": 927,
                    "end": 1025,
                    "loc": {
                      "start": {
                        "line": 21,
                        "column": 8
                      },
                      "end": {
                        "line": 21,
                        "column": 106
                      }
                    },
                    "argument": {
                      "type": "StringLiteral",
                      "start": 934,
                      "end": 1024,
                      "loc": {
                        "start": {
                          "line": 21,
                          "column": 15
                        },
                        "end": {
                          "line": 21,
                          "column": 105
                        }
                      },
                      "extra": {
                        "rawValue": "https://fonts.googleapis.com/css2?family=Cardo&family=Lato:wght@100;300;400&display=swap",
                        "raw": "\"https://fonts.googleapis.com/css2?family=Cardo&family=Lato:wght@100;300;400&display=swap\""
                      },
                      "value": "https://fonts.googleapis.com/css2?family=Cardo&family=Lato:wght@100;300;400&display=swap"
                    }
                  }
                ],
                "directives": []
              }
            },
            {
              "type": "ClassMethod",
              "start": 1040,
              "end": 1189,
              "loc": {
                "start": {
                  "line": 23,
                  "column": 6
                },
                "end": {
                  "line": 25,
                  "column": 7
                }
              },
              "static": true,
              "computed": false,
              "key": {
                "type": "Identifier",
                "start": 1051,
                "end": 1061,
                "loc": {
                  "start": {
                    "line": 23,
                    "column": 17
                  },
                  "end": {
                    "line": 23,
                    "column": 27
                  },
                  "identifierName": "ArrowEmail"
                },
                "name": "ArrowEmail"
              },
              "kind": "get",
              "id": null,
              "generator": false,
              "expression": false,
              "async": false,
              "params": [],
              "body": {
                "type": "BlockStatement",
                "start": 1064,
                "end": 1189,
                "loc": {
                  "start": {
                    "line": 23,
                    "column": 30
                  },
                  "end": {
                    "line": 25,
                    "column": 7
                  }
                },
                "body": [
                  {
                    "type": "ReturnStatement",
                    "start": 1074,
                    "end": 1181,
                    "loc": {
                      "start": {
                        "line": 24,
                        "column": 8
                      },
                      "end": {
                        "line": 24,
                        "column": 115
                      }
                    },
                    "argument": {
                      "type": "StringLiteral",
                      "start": 1081,
                      "end": 1180,
                      "loc": {
                        "start": {
                          "line": 24,
                          "column": 15
                        },
                        "end": {
                          "line": 24,
                          "column": 114
                        }
                      },
                      "extra": {
                        "rawValue": "https://cdn.discordapp.com/attachments/973237631959855234/1121759694952857610/Clip_path_group.png",
                        "raw": "\"https://cdn.discordapp.com/attachments/973237631959855234/1121759694952857610/Clip_path_group.png\""
                      },
                      "value": "https://cdn.discordapp.com/attachments/973237631959855234/1121759694952857610/Clip_path_group.png"
                    }
                  }
                ],
                "directives": []
              }
            }
          ]
        },
        "name": "_",
        "leadingComments": [],
        "trailingComments": []
      },
      {
        "type": "Identifier",
        "start": 1194,
        "end": 1219,
        "loc": {
          "start": {
            "line": 29,
            "column": 0
          },
          "end": {
            "line": 29,
            "column": 25
          }
        },
        "declaration": {
          "type": "Identifier",
          "start": 1209,
          "end": 1218,
          "loc": {
            "start": {
              "line": 29,
              "column": 15
            },
            "end": {
              "line": 29,
              "column": 24
            },
            "identifierName": "Constants"
          },
          "name": "Constants"
        },
        "name": "_",
        "leadingComments": [],
        "trailingComments": []
      },
      {
        "type": "ExportDefaultDeclaration",
        "start": 1194,
        "end": 1219,
        "loc": {
          "start": {
            "line": 29,
            "column": 0
          },
          "end": {
            "line": 29,
            "column": 25
          }
        },
        "declaration": {
          "type": "ClassDeclaration",
          "start": 0,
          "end": 1191,
          "loc": {
            "start": {
              "line": 1,
              "column": 0
            },
            "end": {
              "line": 26,
              "column": 1
            }
          },
          "id": {
            "type": "Identifier",
            "start": 6,
            "end": 15,
            "loc": {
              "start": {
                "line": 1,
                "column": 6
              },
              "end": {
                "line": 1,
                "column": 15
              },
              "identifierName": "Constants"
            },
            "name": "Constants"
          },
          "superClass": null,
          "body": {
            "type": "ClassBody",
            "start": 16,
            "end": 1191,
            "loc": {
              "start": {
                "line": 1,
                "column": 16
              },
              "end": {
                "line": 26,
                "column": 1
              }
            },
            "body": [
              {
                "type": "ClassMethod",
                "start": 24,
                "end": 118,
                "loc": {
                  "start": {
                    "line": 2,
                    "column": 6
                  },
                  "end": {
                    "line": 4,
                    "column": 7
                  }
                },
                "static": true,
                "computed": false,
                "key": {
                  "type": "Identifier",
                  "start": 35,
                  "end": 42,
                  "loc": {
                    "start": {
                      "line": 2,
                      "column": 17
                    },
                    "end": {
                      "line": 2,
                      "column": 24
                    },
                    "identifierName": "FontPdf"
                  },
                  "name": "FontPdf"
                },
                "kind": "get",
                "id": null,
                "generator": false,
                "expression": false,
                "async": false,
                "params": [],
                "body": {
                  "type": "BlockStatement",
                  "start": 45,
                  "end": 118,
                  "loc": {
                    "start": {
                      "line": 2,
                      "column": 27
                    },
                    "end": {
                      "line": 4,
                      "column": 7
                    }
                  },
                  "body": [
                    {
                      "type": "ReturnStatement",
                      "start": 55,
                      "end": 110,
                      "loc": {
                        "start": {
                          "line": 3,
                          "column": 8
                        },
                        "end": {
                          "line": 3,
                          "column": 63
                        }
                      },
                      "argument": {
                        "type": "StringLiteral",
                        "start": 62,
                        "end": 109,
                        "loc": {
                          "start": {
                            "line": 3,
                            "column": 15
                          },
                          "end": {
                            "line": 3,
                            "column": 62
                          }
                        },
                        "extra": {
                          "rawValue": "https://fonts.cdnfonts.com/css/sst-typewriter",
                          "raw": "'https://fonts.cdnfonts.com/css/sst-typewriter'"
                        },
                        "value": "https://fonts.cdnfonts.com/css/sst-typewriter"
                      }
                    }
                  ],
                  "directives": []
                }
              },
              {
                "type": "ClassMethod",
                "start": 125,
                "end": 269,
                "loc": {
                  "start": {
                    "line": 5,
                    "column": 6
                  },
                  "end": {
                    "line": 7,
                    "column": 7
                  }
                },
                "static": true,
                "computed": false,
                "key": {
                  "type": "Identifier",
                  "start": 136,
                  "end": 150,
                  "loc": {
                    "start": {
                      "line": 5,
                      "column": 17
                    },
                    "end": {
                      "line": 5,
                      "column": 31
                    },
                    "identifierName": "LogoFedrannPdf"
                  },
                  "name": "LogoFedrannPdf"
                },
                "kind": "get",
                "id": null,
                "generator": false,
                "expression": false,
                "async": false,
                "params": [],
                "body": {
                  "type": "BlockStatement",
                  "start": 153,
                  "end": 269,
                  "loc": {
                    "start": {
                      "line": 5,
                      "column": 34
                    },
                    "end": {
                      "line": 7,
                      "column": 7
                    }
                  },
                  "body": [
                    {
                      "type": "ReturnStatement",
                      "start": 163,
                      "end": 261,
                      "loc": {
                        "start": {
                          "line": 6,
                          "column": 8
                        },
                        "end": {
                          "line": 6,
                          "column": 106
                        }
                      },
                      "argument": {
                        "type": "StringLiteral",
                        "start": 170,
                        "end": 260,
                        "loc": {
                          "start": {
                            "line": 6,
                            "column": 15
                          },
                          "end": {
                            "line": 6,
                            "column": 105
                          }
                        },
                        "extra": {
                          "rawValue": "https://cdn.discordapp.com/attachments/973237631959855234/1118854023995465758/Logo_1.png",
                          "raw": "\"https://cdn.discordapp.com/attachments/973237631959855234/1118854023995465758/Logo_1.png\""
                        },
                        "value": "https://cdn.discordapp.com/attachments/973237631959855234/1118854023995465758/Logo_1.png"
                      }
                    }
                  ],
                  "directives": []
                }
              },
              {
                "type": "ClassMethod",
                "start": 276,
                "end": 422,
                "loc": {
                  "start": {
                    "line": 8,
                    "column": 6
                  },
                  "end": {
                    "line": 10,
                    "column": 7
                  }
                },
                "static": true,
                "computed": false,
                "key": {
                  "type": "Identifier",
                  "start": 287,
                  "end": 299,
                  "loc": {
                    "start": {
                      "line": 8,
                      "column": 17
                    },
                    "end": {
                      "line": 8,
                      "column": 29
                    },
                    "identifierName": "LecturePhoto"
                  },
                  "name": "LecturePhoto"
                },
                "kind": "get",
                "id": null,
                "generator": false,
                "expression": false,
                "async": false,
                "params": [],
                "body": {
                  "type": "BlockStatement",
                  "start": 302,
                  "end": 422,
                  "loc": {
                    "start": {
                      "line": 8,
                      "column": 32
                    },
                    "end": {
                      "line": 10,
                      "column": 7
                    }
                  },
                  "body": [
                    {
                      "type": "ReturnStatement",
                      "start": 312,
                      "end": 414,
                      "loc": {
                        "start": {
                          "line": 9,
                          "column": 8
                        },
                        "end": {
                          "line": 9,
                          "column": 110
                        }
                      },
                      "argument": {
                        "type": "StringLiteral",
                        "start": 319,
                        "end": 413,
                        "loc": {
                          "start": {
                            "line": 9,
                            "column": 15
                          },
                          "end": {
                            "line": 9,
                            "column": 109
                          }
                        },
                        "extra": {
                          "rawValue": "https://cdn.discordapp.com/attachments/973237631959855234/1121098716846227526/DSC05369_1.png",
                          "raw": "\"https://cdn.discordapp.com/attachments/973237631959855234/1121098716846227526/DSC05369_1.png\""
                        },
                        "value": "https://cdn.discordapp.com/attachments/973237631959855234/1121098716846227526/DSC05369_1.png"
                      }
                    }
                  ],
                  "directives": []
                }
              },
              {
                "type": "ClassMethod",
                "start": 429,
                "end": 580,
                "loc": {
                  "start": {
                    "line": 11,
                    "column": 6
                  },
                  "end": {
                    "line": 13,
                    "column": 7
                  }
                },
                "static": true,
                "computed": false,
                "key": {
                  "type": "Identifier",
                  "start": 440,
                  "end": 449,
                  "loc": {
                    "start": {
                      "line": 11,
                      "column": 17
                    },
                    "end": {
                      "line": 11,
                      "column": 26
                    },
                    "identifierName": "LockPhoto"
                  },
                  "name": "LockPhoto"
                },
                "kind": "get",
                "id": null,
                "generator": false,
                "expression": false,
                "async": false,
                "params": [],
                "body": {
                  "type": "BlockStatement",
                  "start": 452,
                  "end": 580,
                  "loc": {
                    "start": {
                      "line": 11,
                      "column": 29
                    },
                    "end": {
                      "line": 13,
                      "column": 7
                    }
                  },
                  "body": [
                    {
                      "type": "ReturnStatement",
                      "start": 462,
                      "end": 572,
                      "loc": {
                        "start": {
                          "line": 12,
                          "column": 8
                        },
                        "end": {
                          "line": 12,
                          "column": 118
                        }
                      },
                      "argument": {
                        "type": "StringLiteral",
                        "start": 469,
                        "end": 571,
                        "loc": {
                          "start": {
                            "line": 12,
                            "column": 15
                          },
                          "end": {
                            "line": 12,
                            "column": 117
                          }
                        },
                        "extra": {
                          "rawValue": "https://cdn.discordapp.com/attachments/973237631959855234/1121430756191899808/cadeado_complexo_2.png",
                          "raw": "\"https://cdn.discordapp.com/attachments/973237631959855234/1121430756191899808/cadeado_complexo_2.png\""
                        },
                        "value": "https://cdn.discordapp.com/attachments/973237631959855234/1121430756191899808/cadeado_complexo_2.png"
                      }
                    }
                  ],
                  "directives": []
                }
              },
              {
                "type": "ClassMethod",
                "start": 587,
                "end": 728,
                "loc": {
                  "start": {
                    "line": 14,
                    "column": 6
                  },
                  "end": {
                    "line": 16,
                    "column": 7
                  }
                },
                "static": true,
                "computed": false,
                "key": {
                  "type": "Identifier",
                  "start": 598,
                  "end": 609,
                  "loc": {
                    "start": {
                      "line": 14,
                      "column": 17
                    },
                    "end": {
                      "line": 14,
                      "column": 28
                    },
                    "identifierName": "TicketPhoto"
                  },
                  "name": "TicketPhoto"
                },
                "kind": "get",
                "id": null,
                "generator": false,
                "expression": false,
                "async": false,
                "params": [],
                "body": {
                  "type": "BlockStatement",
                  "start": 612,
                  "end": 728,
                  "loc": {
                    "start": {
                      "line": 14,
                      "column": 31
                    },
                    "end": {
                      "line": 16,
                      "column": 7
                    }
                  },
                  "body": [
                    {
                      "type": "ReturnStatement",
                      "start": 622,
                      "end": 720,
                      "loc": {
                        "start": {
                          "line": 15,
                          "column": 8
                        },
                        "end": {
                          "line": 15,
                          "column": 106
                        }
                      },
                      "argument": {
                        "type": "StringLiteral",
                        "start": 629,
                        "end": 719,
                        "loc": {
                          "start": {
                            "line": 15,
                            "column": 15
                          },
                          "end": {
                            "line": 15,
                            "column": 105
                          }
                        },
                        "extra": {
                          "rawValue": "https://cdn.discordapp.com/attachments/973237631959855234/1121430325575286904/ticket.png",
                          "raw": "\"https://cdn.discordapp.com/attachments/973237631959855234/1121430325575286904/ticket.png\""
                        },
                        "value": "https://cdn.discordapp.com/attachments/973237631959855234/1121430325575286904/ticket.png"
                      }
                    }
                  ],
                  "directives": []
                }
              },
              {
                "type": "ClassMethod",
                "start": 735,
                "end": 880,
                "loc": {
                  "start": {
                    "line": 17,
                    "column": 6
                  },
                  "end": {
                    "line": 19,
                    "column": 7
                  }
                },
                "static": true,
                "computed": false,
                "key": {
                  "type": "Identifier",
                  "start": 746,
                  "end": 756,
                  "loc": {
                    "start": {
                      "line": 17,
                      "column": 17
                    },
                    "end": {
                      "line": 17,
                      "column": 27
                    },
                    "identifierName": "ClockPhoto"
                  },
                  "name": "ClockPhoto"
                },
                "kind": "get",
                "id": null,
                "generator": false,
                "expression": false,
                "async": false,
                "params": [],
                "body": {
                  "type": "BlockStatement",
                  "start": 759,
                  "end": 880,
                  "loc": {
                    "start": {
                      "line": 17,
                      "column": 30
                    },
                    "end": {
                      "line": 19,
                      "column": 7
                    }
                  },
                  "body": [
                    {
                      "type": "ReturnStatement",
                      "start": 769,
                      "end": 872,
                      "loc": {
                        "start": {
                          "line": 18,
                          "column": 8
                        },
                        "end": {
                          "line": 18,
                          "column": 111
                        }
                      },
                      "argument": {
                        "type": "StringLiteral",
                        "start": 776,
                        "end": 871,
                        "loc": {
                          "start": {
                            "line": 18,
                            "column": 15
                          },
                          "end": {
                            "line": 18,
                            "column": 110
                          }
                        },
                        "extra": {
                          "rawValue": "https://cdn.discordapp.com/attachments/973237631959855234/1121102237108813864/Rectangle_3.png",
                          "raw": "\"https://cdn.discordapp.com/attachments/973237631959855234/1121102237108813864/Rectangle_3.png\""
                        },
                        "value": "https://cdn.discordapp.com/attachments/973237631959855234/1121102237108813864/Rectangle_3.png"
                      }
                    }
                  ],
                  "directives": []
                }
              },
              {
                "type": "ClassMethod",
                "start": 887,
                "end": 1033,
                "loc": {
                  "start": {
                    "line": 20,
                    "column": 6
                  },
                  "end": {
                    "line": 22,
                    "column": 7
                  }
                },
                "static": true,
                "computed": false,
                "key": {
                  "type": "Identifier",
                  "start": 898,
                  "end": 914,
                  "loc": {
                    "start": {
                      "line": 20,
                      "column": 17
                    },
                    "end": {
                      "line": 20,
                      "column": 33
                    },
                    "identifierName": "FontConfirmEmail"
                  },
                  "name": "FontConfirmEmail"
                },
                "kind": "get",
                "id": null,
                "generator": false,
                "expression": false,
                "async": false,
                "params": [],
                "body": {
                  "type": "BlockStatement",
                  "start": 917,
                  "end": 1033,
                  "loc": {
                    "start": {
                      "line": 20,
                      "column": 36
                    },
                    "end": {
                      "line": 22,
                      "column": 7
                    }
                  },
                  "body": [
                    {
                      "type": "ReturnStatement",
                      "start": 927,
                      "end": 1025,
                      "loc": {
                        "start": {
                          "line": 21,
                          "column": 8
                        },
                        "end": {
                          "line": 21,
                          "column": 106
                        }
                      },
                      "argument": {
                        "type": "StringLiteral",
                        "start": 934,
                        "end": 1024,
                        "loc": {
                          "start": {
                            "line": 21,
                            "column": 15
                          },
                          "end": {
                            "line": 21,
                            "column": 105
                          }
                        },
                        "extra": {
                          "rawValue": "https://fonts.googleapis.com/css2?family=Cardo&family=Lato:wght@100;300;400&display=swap",
                          "raw": "\"https://fonts.googleapis.com/css2?family=Cardo&family=Lato:wght@100;300;400&display=swap\""
                        },
                        "value": "https://fonts.googleapis.com/css2?family=Cardo&family=Lato:wght@100;300;400&display=swap"
                      }
                    }
                  ],
                  "directives": []
                }
              },
              {
                "type": "ClassMethod",
                "start": 1040,
                "end": 1189,
                "loc": {
                  "start": {
                    "line": 23,
                    "column": 6
                  },
                  "end": {
                    "line": 25,
                    "column": 7
                  }
                },
                "static": true,
                "computed": false,
                "key": {
                  "type": "Identifier",
                  "start": 1051,
                  "end": 1061,
                  "loc": {
                    "start": {
                      "line": 23,
                      "column": 17
                    },
                    "end": {
                      "line": 23,
                      "column": 27
                    },
                    "identifierName": "ArrowEmail"
                  },
                  "name": "ArrowEmail"
                },
                "kind": "get",
                "id": null,
                "generator": false,
                "expression": false,
                "async": false,
                "params": [],
                "body": {
                  "type": "BlockStatement",
                  "start": 1064,
                  "end": 1189,
                  "loc": {
                    "start": {
                      "line": 23,
                      "column": 30
                    },
                    "end": {
                      "line": 25,
                      "column": 7
                    }
                  },
                  "body": [
                    {
                      "type": "ReturnStatement",
                      "start": 1074,
                      "end": 1181,
                      "loc": {
                        "start": {
                          "line": 24,
                          "column": 8
                        },
                        "end": {
                          "line": 24,
                          "column": 115
                        }
                      },
                      "argument": {
                        "type": "StringLiteral",
                        "start": 1081,
                        "end": 1180,
                        "loc": {
                          "start": {
                            "line": 24,
                            "column": 15
                          },
                          "end": {
                            "line": 24,
                            "column": 114
                          }
                        },
                        "extra": {
                          "rawValue": "https://cdn.discordapp.com/attachments/973237631959855234/1121759694952857610/Clip_path_group.png",
                          "raw": "\"https://cdn.discordapp.com/attachments/973237631959855234/1121759694952857610/Clip_path_group.png\""
                        },
                        "value": "https://cdn.discordapp.com/attachments/973237631959855234/1121759694952857610/Clip_path_group.png"
                      }
                    }
                  ],
                  "directives": []
                }
              }
            ]
          },
          "__PseudoExport__": false,
          "leadingComments": [],
          "trailingComments": []
        },
        "leadingComments": null
      }
    ],
    "directives": []
  },
  "comments": [],
  "tokens": [
    {
      "type": {
        "label": "class",
        "keyword": "class",
        "beforeExpr": false,
        "startsExpr": false,
        "rightAssociative": false,
        "isLoop": false,
        "isAssign": false,
        "prefix": false,
        "postfix": false,
        "binop": null,
        "updateContext": null
      },
      "value": "class",
      "start": 0,
      "end": 5,
      "loc": {
        "start": {
          "line": 1,
          "column": 0
        },
        "end": {
          "line": 1,
          "column": 5
        }
      }
    },
    {
      "type": {
        "label": "name",
        "beforeExpr": false,
        "startsExpr": true,
        "rightAssociative": false,
        "isLoop": false,
        "isAssign": false,
        "prefix": false,
        "postfix": false,
        "binop": null
      },
      "value": "Constants",
      "start": 6,
      "end": 15,
      "loc": {
        "start": {
          "line": 1,
          "column": 6
        },
        "end": {
          "line": 1,
          "column": 15
        }
      }
    },
    {
      "type": {
        "label": "{",
        "beforeExpr": true,
        "startsExpr": true,
        "rightAssociative": false,
        "isLoop": false,
        "isAssign": false,
        "prefix": false,
        "postfix": false,
        "binop": null
      },
      "start": 16,
      "end": 17,
      "loc": {
        "start": {
          "line": 1,
          "column": 16
        },
        "end": {
          "line": 1,
          "column": 17
        }
      }
    },
    {
      "type": {
        "label": "name",
        "beforeExpr": false,
        "startsExpr": true,
        "rightAssociative": false,
        "isLoop": false,
        "isAssign": false,
        "prefix": false,
        "postfix": false,
        "binop": null
      },
      "value": "static",
      "start": 24,
      "end": 30,
      "loc": {
        "start": {
          "line": 2,
          "column": 6
        },
        "end": {
          "line": 2,
          "column": 12
        }
      }
    },
    {
      "type": {
        "label": "name",
        "beforeExpr": false,
        "startsExpr": true,
        "rightAssociative": false,
        "isLoop": false,
        "isAssign": false,
        "prefix": false,
        "postfix": false,
        "binop": null
      },
      "value": "get",
      "start": 31,
      "end": 34,
      "loc": {
        "start": {
          "line": 2,
          "column": 13
        },
        "end": {
          "line": 2,
          "column": 16
        }
      }
    },
    {
      "type": {
        "label": "name",
        "beforeExpr": false,
        "startsExpr": true,
        "rightAssociative": false,
        "isLoop": false,
        "isAssign": false,
        "prefix": false,
        "postfix": false,
        "binop": null
      },
      "value": "FontPdf",
      "start": 35,
      "end": 42,
      "loc": {
        "start": {
          "line": 2,
          "column": 17
        },
        "end": {
          "line": 2,
          "column": 24
        }
      }
    },
    {
      "type": {
        "label": "(",
        "beforeExpr": true,
        "startsExpr": true,
        "rightAssociative": false,
        "isLoop": false,
        "isAssign": false,
        "prefix": false,
        "postfix": false,
        "binop": null
      },
      "start": 42,
      "end": 43,
      "loc": {
        "start": {
          "line": 2,
          "column": 24
        },
        "end": {
          "line": 2,
          "column": 25
        }
      }
    },
    {
      "type": {
        "label": ")",
        "beforeExpr": false,
        "startsExpr": false,
        "rightAssociative": false,
        "isLoop": false,
        "isAssign": false,
        "prefix": false,
        "postfix": false,
        "binop": null
      },
      "start": 43,
      "end": 44,
      "loc": {
        "start": {
          "line": 2,
          "column": 25
        },
        "end": {
          "line": 2,
          "column": 26
        }
      }
    },
    {
      "type": {
        "label": "{",
        "beforeExpr": true,
        "startsExpr": true,
        "rightAssociative": false,
        "isLoop": false,
        "isAssign": false,
        "prefix": false,
        "postfix": false,
        "binop": null
      },
      "start": 45,
      "end": 46,
      "loc": {
        "start": {
          "line": 2,
          "column": 27
        },
        "end": {
          "line": 2,
          "column": 28
        }
      }
    },
    {
      "type": {
        "label": "return",
        "keyword": "return",
        "beforeExpr": true,
        "startsExpr": false,
        "rightAssociative": false,
        "isLoop": false,
        "isAssign": false,
        "prefix": false,
        "postfix": false,
        "binop": null,
        "updateContext": null
      },
      "value": "return",
      "start": 55,
      "end": 61,
      "loc": {
        "start": {
          "line": 3,
          "column": 8
        },
        "end": {
          "line": 3,
          "column": 14
        }
      }
    },
    {
      "type": {
        "label": "string",
        "beforeExpr": false,
        "startsExpr": true,
        "rightAssociative": false,
        "isLoop": false,
        "isAssign": false,
        "prefix": false,
        "postfix": false,
        "binop": null,
        "updateContext": null
      },
      "value": "https://fonts.cdnfonts.com/css/sst-typewriter",
      "start": 62,
      "end": 109,
      "loc": {
        "start": {
          "line": 3,
          "column": 15
        },
        "end": {
          "line": 3,
          "column": 62
        }
      }
    },
    {
      "type": {
        "label": ";",
        "beforeExpr": true,
        "startsExpr": false,
        "rightAssociative": false,
        "isLoop": false,
        "isAssign": false,
        "prefix": false,
        "postfix": false,
        "binop": null,
        "updateContext": null
      },
      "start": 109,
      "end": 110,
      "loc": {
        "start": {
          "line": 3,
          "column": 62
        },
        "end": {
          "line": 3,
          "column": 63
        }
      }
    },
    {
      "type": {
        "label": "}",
        "beforeExpr": false,
        "startsExpr": false,
        "rightAssociative": false,
        "isLoop": false,
        "isAssign": false,
        "prefix": false,
        "postfix": false,
        "binop": null
      },
      "start": 117,
      "end": 118,
      "loc": {
        "start": {
          "line": 4,
          "column": 6
        },
        "end": {
          "line": 4,
          "column": 7
        }
      }
    },
    {
      "type": {
        "label": "name",
        "beforeExpr": false,
        "startsExpr": true,
        "rightAssociative": false,
        "isLoop": false,
        "isAssign": false,
        "prefix": false,
        "postfix": false,
        "binop": null
      },
      "value": "static",
      "start": 125,
      "end": 131,
      "loc": {
        "start": {
          "line": 5,
          "column": 6
        },
        "end": {
          "line": 5,
          "column": 12
        }
      }
    },
    {
      "type": {
        "label": "name",
        "beforeExpr": false,
        "startsExpr": true,
        "rightAssociative": false,
        "isLoop": false,
        "isAssign": false,
        "prefix": false,
        "postfix": false,
        "binop": null
      },
      "value": "get",
      "start": 132,
      "end": 135,
      "loc": {
        "start": {
          "line": 5,
          "column": 13
        },
        "end": {
          "line": 5,
          "column": 16
        }
      }
    },
    {
      "type": {
        "label": "name",
        "beforeExpr": false,
        "startsExpr": true,
        "rightAssociative": false,
        "isLoop": false,
        "isAssign": false,
        "prefix": false,
        "postfix": false,
        "binop": null
      },
      "value": "LogoFedrannPdf",
      "start": 136,
      "end": 150,
      "loc": {
        "start": {
          "line": 5,
          "column": 17
        },
        "end": {
          "line": 5,
          "column": 31
        }
      }
    },
    {
      "type": {
        "label": "(",
        "beforeExpr": true,
        "startsExpr": true,
        "rightAssociative": false,
        "isLoop": false,
        "isAssign": false,
        "prefix": false,
        "postfix": false,
        "binop": null
      },
      "start": 150,
      "end": 151,
      "loc": {
        "start": {
          "line": 5,
          "column": 31
        },
        "end": {
          "line": 5,
          "column": 32
        }
      }
    },
    {
      "type": {
        "label": ")",
        "beforeExpr": false,
        "startsExpr": false,
        "rightAssociative": false,
        "isLoop": false,
        "isAssign": false,
        "prefix": false,
        "postfix": false,
        "binop": null
      },
      "start": 151,
      "end": 152,
      "loc": {
        "start": {
          "line": 5,
          "column": 32
        },
        "end": {
          "line": 5,
          "column": 33
        }
      }
    },
    {
      "type": {
        "label": "{",
        "beforeExpr": true,
        "startsExpr": true,
        "rightAssociative": false,
        "isLoop": false,
        "isAssign": false,
        "prefix": false,
        "postfix": false,
        "binop": null
      },
      "start": 153,
      "end": 154,
      "loc": {
        "start": {
          "line": 5,
          "column": 34
        },
        "end": {
          "line": 5,
          "column": 35
        }
      }
    },
    {
      "type": {
        "label": "return",
        "keyword": "return",
        "beforeExpr": true,
        "startsExpr": false,
        "rightAssociative": false,
        "isLoop": false,
        "isAssign": false,
        "prefix": false,
        "postfix": false,
        "binop": null,
        "updateContext": null
      },
      "value": "return",
      "start": 163,
      "end": 169,
      "loc": {
        "start": {
          "line": 6,
          "column": 8
        },
        "end": {
          "line": 6,
          "column": 14
        }
      }
    },
    {
      "type": {
        "label": "string",
        "beforeExpr": false,
        "startsExpr": true,
        "rightAssociative": false,
        "isLoop": false,
        "isAssign": false,
        "prefix": false,
        "postfix": false,
        "binop": null,
        "updateContext": null
      },
      "value": "https://cdn.discordapp.com/attachments/973237631959855234/1118854023995465758/Logo_1.png",
      "start": 170,
      "end": 260,
      "loc": {
        "start": {
          "line": 6,
          "column": 15
        },
        "end": {
          "line": 6,
          "column": 105
        }
      }
    },
    {
      "type": {
        "label": ";",
        "beforeExpr": true,
        "startsExpr": false,
        "rightAssociative": false,
        "isLoop": false,
        "isAssign": false,
        "prefix": false,
        "postfix": false,
        "binop": null,
        "updateContext": null
      },
      "start": 260,
      "end": 261,
      "loc": {
        "start": {
          "line": 6,
          "column": 105
        },
        "end": {
          "line": 6,
          "column": 106
        }
      }
    },
    {
      "type": {
        "label": "}",
        "beforeExpr": false,
        "startsExpr": false,
        "rightAssociative": false,
        "isLoop": false,
        "isAssign": false,
        "prefix": false,
        "postfix": false,
        "binop": null
      },
      "start": 268,
      "end": 269,
      "loc": {
        "start": {
          "line": 7,
          "column": 6
        },
        "end": {
          "line": 7,
          "column": 7
        }
      }
    },
    {
      "type": {
        "label": "name",
        "beforeExpr": false,
        "startsExpr": true,
        "rightAssociative": false,
        "isLoop": false,
        "isAssign": false,
        "prefix": false,
        "postfix": false,
        "binop": null
      },
      "value": "static",
      "start": 276,
      "end": 282,
      "loc": {
        "start": {
          "line": 8,
          "column": 6
        },
        "end": {
          "line": 8,
          "column": 12
        }
      }
    },
    {
      "type": {
        "label": "name",
        "beforeExpr": false,
        "startsExpr": true,
        "rightAssociative": false,
        "isLoop": false,
        "isAssign": false,
        "prefix": false,
        "postfix": false,
        "binop": null
      },
      "value": "get",
      "start": 283,
      "end": 286,
      "loc": {
        "start": {
          "line": 8,
          "column": 13
        },
        "end": {
          "line": 8,
          "column": 16
        }
      }
    },
    {
      "type": {
        "label": "name",
        "beforeExpr": false,
        "startsExpr": true,
        "rightAssociative": false,
        "isLoop": false,
        "isAssign": false,
        "prefix": false,
        "postfix": false,
        "binop": null
      },
      "value": "LecturePhoto",
      "start": 287,
      "end": 299,
      "loc": {
        "start": {
          "line": 8,
          "column": 17
        },
        "end": {
          "line": 8,
          "column": 29
        }
      }
    },
    {
      "type": {
        "label": "(",
        "beforeExpr": true,
        "startsExpr": true,
        "rightAssociative": false,
        "isLoop": false,
        "isAssign": false,
        "prefix": false,
        "postfix": false,
        "binop": null
      },
      "start": 299,
      "end": 300,
      "loc": {
        "start": {
          "line": 8,
          "column": 29
        },
        "end": {
          "line": 8,
          "column": 30
        }
      }
    },
    {
      "type": {
        "label": ")",
        "beforeExpr": false,
        "startsExpr": false,
        "rightAssociative": false,
        "isLoop": false,
        "isAssign": false,
        "prefix": false,
        "postfix": false,
        "binop": null
      },
      "start": 300,
      "end": 301,
      "loc": {
        "start": {
          "line": 8,
          "column": 30
        },
        "end": {
          "line": 8,
          "column": 31
        }
      }
    },
    {
      "type": {
        "label": "{",
        "beforeExpr": true,
        "startsExpr": true,
        "rightAssociative": false,
        "isLoop": false,
        "isAssign": false,
        "prefix": false,
        "postfix": false,
        "binop": null
      },
      "start": 302,
      "end": 303,
      "loc": {
        "start": {
          "line": 8,
          "column": 32
        },
        "end": {
          "line": 8,
          "column": 33
        }
      }
    },
    {
      "type": {
        "label": "return",
        "keyword": "return",
        "beforeExpr": true,
        "startsExpr": false,
        "rightAssociative": false,
        "isLoop": false,
        "isAssign": false,
        "prefix": false,
        "postfix": false,
        "binop": null,
        "updateContext": null
      },
      "value": "return",
      "start": 312,
      "end": 318,
      "loc": {
        "start": {
          "line": 9,
          "column": 8
        },
        "end": {
          "line": 9,
          "column": 14
        }
      }
    },
    {
      "type": {
        "label": "string",
        "beforeExpr": false,
        "startsExpr": true,
        "rightAssociative": false,
        "isLoop": false,
        "isAssign": false,
        "prefix": false,
        "postfix": false,
        "binop": null,
        "updateContext": null
      },
      "value": "https://cdn.discordapp.com/attachments/973237631959855234/1121098716846227526/DSC05369_1.png",
      "start": 319,
      "end": 413,
      "loc": {
        "start": {
          "line": 9,
          "column": 15
        },
        "end": {
          "line": 9,
          "column": 109
        }
      }
    },
    {
      "type": {
        "label": ";",
        "beforeExpr": true,
        "startsExpr": false,
        "rightAssociative": false,
        "isLoop": false,
        "isAssign": false,
        "prefix": false,
        "postfix": false,
        "binop": null,
        "updateContext": null
      },
      "start": 413,
      "end": 414,
      "loc": {
        "start": {
          "line": 9,
          "column": 109
        },
        "end": {
          "line": 9,
          "column": 110
        }
      }
    },
    {
      "type": {
        "label": "}",
        "beforeExpr": false,
        "startsExpr": false,
        "rightAssociative": false,
        "isLoop": false,
        "isAssign": false,
        "prefix": false,
        "postfix": false,
        "binop": null
      },
      "start": 421,
      "end": 422,
      "loc": {
        "start": {
          "line": 10,
          "column": 6
        },
        "end": {
          "line": 10,
          "column": 7
        }
      }
    },
    {
      "type": {
        "label": "name",
        "beforeExpr": false,
        "startsExpr": true,
        "rightAssociative": false,
        "isLoop": false,
        "isAssign": false,
        "prefix": false,
        "postfix": false,
        "binop": null
      },
      "value": "static",
      "start": 429,
      "end": 435,
      "loc": {
        "start": {
          "line": 11,
          "column": 6
        },
        "end": {
          "line": 11,
          "column": 12
        }
      }
    },
    {
      "type": {
        "label": "name",
        "beforeExpr": false,
        "startsExpr": true,
        "rightAssociative": false,
        "isLoop": false,
        "isAssign": false,
        "prefix": false,
        "postfix": false,
        "binop": null
      },
      "value": "get",
      "start": 436,
      "end": 439,
      "loc": {
        "start": {
          "line": 11,
          "column": 13
        },
        "end": {
          "line": 11,
          "column": 16
        }
      }
    },
    {
      "type": {
        "label": "name",
        "beforeExpr": false,
        "startsExpr": true,
        "rightAssociative": false,
        "isLoop": false,
        "isAssign": false,
        "prefix": false,
        "postfix": false,
        "binop": null
      },
      "value": "LockPhoto",
      "start": 440,
      "end": 449,
      "loc": {
        "start": {
          "line": 11,
          "column": 17
        },
        "end": {
          "line": 11,
          "column": 26
        }
      }
    },
    {
      "type": {
        "label": "(",
        "beforeExpr": true,
        "startsExpr": true,
        "rightAssociative": false,
        "isLoop": false,
        "isAssign": false,
        "prefix": false,
        "postfix": false,
        "binop": null
      },
      "start": 449,
      "end": 450,
      "loc": {
        "start": {
          "line": 11,
          "column": 26
        },
        "end": {
          "line": 11,
          "column": 27
        }
      }
    },
    {
      "type": {
        "label": ")",
        "beforeExpr": false,
        "startsExpr": false,
        "rightAssociative": false,
        "isLoop": false,
        "isAssign": false,
        "prefix": false,
        "postfix": false,
        "binop": null
      },
      "start": 450,
      "end": 451,
      "loc": {
        "start": {
          "line": 11,
          "column": 27
        },
        "end": {
          "line": 11,
          "column": 28
        }
      }
    },
    {
      "type": {
        "label": "{",
        "beforeExpr": true,
        "startsExpr": true,
        "rightAssociative": false,
        "isLoop": false,
        "isAssign": false,
        "prefix": false,
        "postfix": false,
        "binop": null
      },
      "start": 452,
      "end": 453,
      "loc": {
        "start": {
          "line": 11,
          "column": 29
        },
        "end": {
          "line": 11,
          "column": 30
        }
      }
    },
    {
      "type": {
        "label": "return",
        "keyword": "return",
        "beforeExpr": true,
        "startsExpr": false,
        "rightAssociative": false,
        "isLoop": false,
        "isAssign": false,
        "prefix": false,
        "postfix": false,
        "binop": null,
        "updateContext": null
      },
      "value": "return",
      "start": 462,
      "end": 468,
      "loc": {
        "start": {
          "line": 12,
          "column": 8
        },
        "end": {
          "line": 12,
          "column": 14
        }
      }
    },
    {
      "type": {
        "label": "string",
        "beforeExpr": false,
        "startsExpr": true,
        "rightAssociative": false,
        "isLoop": false,
        "isAssign": false,
        "prefix": false,
        "postfix": false,
        "binop": null,
        "updateContext": null
      },
      "value": "https://cdn.discordapp.com/attachments/973237631959855234/1121430756191899808/cadeado_complexo_2.png",
      "start": 469,
      "end": 571,
      "loc": {
        "start": {
          "line": 12,
          "column": 15
        },
        "end": {
          "line": 12,
          "column": 117
        }
      }
    },
    {
      "type": {
        "label": ";",
        "beforeExpr": true,
        "startsExpr": false,
        "rightAssociative": false,
        "isLoop": false,
        "isAssign": false,
        "prefix": false,
        "postfix": false,
        "binop": null,
        "updateContext": null
      },
      "start": 571,
      "end": 572,
      "loc": {
        "start": {
          "line": 12,
          "column": 117
        },
        "end": {
          "line": 12,
          "column": 118
        }
      }
    },
    {
      "type": {
        "label": "}",
        "beforeExpr": false,
        "startsExpr": false,
        "rightAssociative": false,
        "isLoop": false,
        "isAssign": false,
        "prefix": false,
        "postfix": false,
        "binop": null
      },
      "start": 579,
      "end": 580,
      "loc": {
        "start": {
          "line": 13,
          "column": 6
        },
        "end": {
          "line": 13,
          "column": 7
        }
      }
    },
    {
      "type": {
        "label": "name",
        "beforeExpr": false,
        "startsExpr": true,
        "rightAssociative": false,
        "isLoop": false,
        "isAssign": false,
        "prefix": false,
        "postfix": false,
        "binop": null
      },
      "value": "static",
      "start": 587,
      "end": 593,
      "loc": {
        "start": {
          "line": 14,
          "column": 6
        },
        "end": {
          "line": 14,
          "column": 12
        }
      }
    },
    {
      "type": {
        "label": "name",
        "beforeExpr": false,
        "startsExpr": true,
        "rightAssociative": false,
        "isLoop": false,
        "isAssign": false,
        "prefix": false,
        "postfix": false,
        "binop": null
      },
      "value": "get",
      "start": 594,
      "end": 597,
      "loc": {
        "start": {
          "line": 14,
          "column": 13
        },
        "end": {
          "line": 14,
          "column": 16
        }
      }
    },
    {
      "type": {
        "label": "name",
        "beforeExpr": false,
        "startsExpr": true,
        "rightAssociative": false,
        "isLoop": false,
        "isAssign": false,
        "prefix": false,
        "postfix": false,
        "binop": null
      },
      "value": "TicketPhoto",
      "start": 598,
      "end": 609,
      "loc": {
        "start": {
          "line": 14,
          "column": 17
        },
        "end": {
          "line": 14,
          "column": 28
        }
      }
    },
    {
      "type": {
        "label": "(",
        "beforeExpr": true,
        "startsExpr": true,
        "rightAssociative": false,
        "isLoop": false,
        "isAssign": false,
        "prefix": false,
        "postfix": false,
        "binop": null
      },
      "start": 609,
      "end": 610,
      "loc": {
        "start": {
          "line": 14,
          "column": 28
        },
        "end": {
          "line": 14,
          "column": 29
        }
      }
    },
    {
      "type": {
        "label": ")",
        "beforeExpr": false,
        "startsExpr": false,
        "rightAssociative": false,
        "isLoop": false,
        "isAssign": false,
        "prefix": false,
        "postfix": false,
        "binop": null
      },
      "start": 610,
      "end": 611,
      "loc": {
        "start": {
          "line": 14,
          "column": 29
        },
        "end": {
          "line": 14,
          "column": 30
        }
      }
    },
    {
      "type": {
        "label": "{",
        "beforeExpr": true,
        "startsExpr": true,
        "rightAssociative": false,
        "isLoop": false,
        "isAssign": false,
        "prefix": false,
        "postfix": false,
        "binop": null
      },
      "start": 612,
      "end": 613,
      "loc": {
        "start": {
          "line": 14,
          "column": 31
        },
        "end": {
          "line": 14,
          "column": 32
        }
      }
    },
    {
      "type": {
        "label": "return",
        "keyword": "return",
        "beforeExpr": true,
        "startsExpr": false,
        "rightAssociative": false,
        "isLoop": false,
        "isAssign": false,
        "prefix": false,
        "postfix": false,
        "binop": null,
        "updateContext": null
      },
      "value": "return",
      "start": 622,
      "end": 628,
      "loc": {
        "start": {
          "line": 15,
          "column": 8
        },
        "end": {
          "line": 15,
          "column": 14
        }
      }
    },
    {
      "type": {
        "label": "string",
        "beforeExpr": false,
        "startsExpr": true,
        "rightAssociative": false,
        "isLoop": false,
        "isAssign": false,
        "prefix": false,
        "postfix": false,
        "binop": null,
        "updateContext": null
      },
      "value": "https://cdn.discordapp.com/attachments/973237631959855234/1121430325575286904/ticket.png",
      "start": 629,
      "end": 719,
      "loc": {
        "start": {
          "line": 15,
          "column": 15
        },
        "end": {
          "line": 15,
          "column": 105
        }
      }
    },
    {
      "type": {
        "label": ";",
        "beforeExpr": true,
        "startsExpr": false,
        "rightAssociative": false,
        "isLoop": false,
        "isAssign": false,
        "prefix": false,
        "postfix": false,
        "binop": null,
        "updateContext": null
      },
      "start": 719,
      "end": 720,
      "loc": {
        "start": {
          "line": 15,
          "column": 105
        },
        "end": {
          "line": 15,
          "column": 106
        }
      }
    },
    {
      "type": {
        "label": "}",
        "beforeExpr": false,
        "startsExpr": false,
        "rightAssociative": false,
        "isLoop": false,
        "isAssign": false,
        "prefix": false,
        "postfix": false,
        "binop": null
      },
      "start": 727,
      "end": 728,
      "loc": {
        "start": {
          "line": 16,
          "column": 6
        },
        "end": {
          "line": 16,
          "column": 7
        }
      }
    },
    {
      "type": {
        "label": "name",
        "beforeExpr": false,
        "startsExpr": true,
        "rightAssociative": false,
        "isLoop": false,
        "isAssign": false,
        "prefix": false,
        "postfix": false,
        "binop": null
      },
      "value": "static",
      "start": 735,
      "end": 741,
      "loc": {
        "start": {
          "line": 17,
          "column": 6
        },
        "end": {
          "line": 17,
          "column": 12
        }
      }
    },
    {
      "type": {
        "label": "name",
        "beforeExpr": false,
        "startsExpr": true,
        "rightAssociative": false,
        "isLoop": false,
        "isAssign": false,
        "prefix": false,
        "postfix": false,
        "binop": null
      },
      "value": "get",
      "start": 742,
      "end": 745,
      "loc": {
        "start": {
          "line": 17,
          "column": 13
        },
        "end": {
          "line": 17,
          "column": 16
        }
      }
    },
    {
      "type": {
        "label": "name",
        "beforeExpr": false,
        "startsExpr": true,
        "rightAssociative": false,
        "isLoop": false,
        "isAssign": false,
        "prefix": false,
        "postfix": false,
        "binop": null
      },
      "value": "ClockPhoto",
      "start": 746,
      "end": 756,
      "loc": {
        "start": {
          "line": 17,
          "column": 17
        },
        "end": {
          "line": 17,
          "column": 27
        }
      }
    },
    {
      "type": {
        "label": "(",
        "beforeExpr": true,
        "startsExpr": true,
        "rightAssociative": false,
        "isLoop": false,
        "isAssign": false,
        "prefix": false,
        "postfix": false,
        "binop": null
      },
      "start": 756,
      "end": 757,
      "loc": {
        "start": {
          "line": 17,
          "column": 27
        },
        "end": {
          "line": 17,
          "column": 28
        }
      }
    },
    {
      "type": {
        "label": ")",
        "beforeExpr": false,
        "startsExpr": false,
        "rightAssociative": false,
        "isLoop": false,
        "isAssign": false,
        "prefix": false,
        "postfix": false,
        "binop": null
      },
      "start": 757,
      "end": 758,
      "loc": {
        "start": {
          "line": 17,
          "column": 28
        },
        "end": {
          "line": 17,
          "column": 29
        }
      }
    },
    {
      "type": {
        "label": "{",
        "beforeExpr": true,
        "startsExpr": true,
        "rightAssociative": false,
        "isLoop": false,
        "isAssign": false,
        "prefix": false,
        "postfix": false,
        "binop": null
      },
      "start": 759,
      "end": 760,
      "loc": {
        "start": {
          "line": 17,
          "column": 30
        },
        "end": {
          "line": 17,
          "column": 31
        }
      }
    },
    {
      "type": {
        "label": "return",
        "keyword": "return",
        "beforeExpr": true,
        "startsExpr": false,
        "rightAssociative": false,
        "isLoop": false,
        "isAssign": false,
        "prefix": false,
        "postfix": false,
        "binop": null,
        "updateContext": null
      },
      "value": "return",
      "start": 769,
      "end": 775,
      "loc": {
        "start": {
          "line": 18,
          "column": 8
        },
        "end": {
          "line": 18,
          "column": 14
        }
      }
    },
    {
      "type": {
        "label": "string",
        "beforeExpr": false,
        "startsExpr": true,
        "rightAssociative": false,
        "isLoop": false,
        "isAssign": false,
        "prefix": false,
        "postfix": false,
        "binop": null,
        "updateContext": null
      },
      "value": "https://cdn.discordapp.com/attachments/973237631959855234/1121102237108813864/Rectangle_3.png",
      "start": 776,
      "end": 871,
      "loc": {
        "start": {
          "line": 18,
          "column": 15
        },
        "end": {
          "line": 18,
          "column": 110
        }
      }
    },
    {
      "type": {
        "label": ";",
        "beforeExpr": true,
        "startsExpr": false,
        "rightAssociative": false,
        "isLoop": false,
        "isAssign": false,
        "prefix": false,
        "postfix": false,
        "binop": null,
        "updateContext": null
      },
      "start": 871,
      "end": 872,
      "loc": {
        "start": {
          "line": 18,
          "column": 110
        },
        "end": {
          "line": 18,
          "column": 111
        }
      }
    },
    {
      "type": {
        "label": "}",
        "beforeExpr": false,
        "startsExpr": false,
        "rightAssociative": false,
        "isLoop": false,
        "isAssign": false,
        "prefix": false,
        "postfix": false,
        "binop": null
      },
      "start": 879,
      "end": 880,
      "loc": {
        "start": {
          "line": 19,
          "column": 6
        },
        "end": {
          "line": 19,
          "column": 7
        }
      }
    },
    {
      "type": {
        "label": "name",
        "beforeExpr": false,
        "startsExpr": true,
        "rightAssociative": false,
        "isLoop": false,
        "isAssign": false,
        "prefix": false,
        "postfix": false,
        "binop": null
      },
      "value": "static",
      "start": 887,
      "end": 893,
      "loc": {
        "start": {
          "line": 20,
          "column": 6
        },
        "end": {
          "line": 20,
          "column": 12
        }
      }
    },
    {
      "type": {
        "label": "name",
        "beforeExpr": false,
        "startsExpr": true,
        "rightAssociative": false,
        "isLoop": false,
        "isAssign": false,
        "prefix": false,
        "postfix": false,
        "binop": null
      },
      "value": "get",
      "start": 894,
      "end": 897,
      "loc": {
        "start": {
          "line": 20,
          "column": 13
        },
        "end": {
          "line": 20,
          "column": 16
        }
      }
    },
    {
      "type": {
        "label": "name",
        "beforeExpr": false,
        "startsExpr": true,
        "rightAssociative": false,
        "isLoop": false,
        "isAssign": false,
        "prefix": false,
        "postfix": false,
        "binop": null
      },
      "value": "FontConfirmEmail",
      "start": 898,
      "end": 914,
      "loc": {
        "start": {
          "line": 20,
          "column": 17
        },
        "end": {
          "line": 20,
          "column": 33
        }
      }
    },
    {
      "type": {
        "label": "(",
        "beforeExpr": true,
        "startsExpr": true,
        "rightAssociative": false,
        "isLoop": false,
        "isAssign": false,
        "prefix": false,
        "postfix": false,
        "binop": null
      },
      "start": 914,
      "end": 915,
      "loc": {
        "start": {
          "line": 20,
          "column": 33
        },
        "end": {
          "line": 20,
          "column": 34
        }
      }
    },
    {
      "type": {
        "label": ")",
        "beforeExpr": false,
        "startsExpr": false,
        "rightAssociative": false,
        "isLoop": false,
        "isAssign": false,
        "prefix": false,
        "postfix": false,
        "binop": null
      },
      "start": 915,
      "end": 916,
      "loc": {
        "start": {
          "line": 20,
          "column": 34
        },
        "end": {
          "line": 20,
          "column": 35
        }
      }
    },
    {
      "type": {
        "label": "{",
        "beforeExpr": true,
        "startsExpr": true,
        "rightAssociative": false,
        "isLoop": false,
        "isAssign": false,
        "prefix": false,
        "postfix": false,
        "binop": null
      },
      "start": 917,
      "end": 918,
      "loc": {
        "start": {
          "line": 20,
          "column": 36
        },
        "end": {
          "line": 20,
          "column": 37
        }
      }
    },
    {
      "type": {
        "label": "return",
        "keyword": "return",
        "beforeExpr": true,
        "startsExpr": false,
        "rightAssociative": false,
        "isLoop": false,
        "isAssign": false,
        "prefix": false,
        "postfix": false,
        "binop": null,
        "updateContext": null
      },
      "value": "return",
      "start": 927,
      "end": 933,
      "loc": {
        "start": {
          "line": 21,
          "column": 8
        },
        "end": {
          "line": 21,
          "column": 14
        }
      }
    },
    {
      "type": {
        "label": "string",
        "beforeExpr": false,
        "startsExpr": true,
        "rightAssociative": false,
        "isLoop": false,
        "isAssign": false,
        "prefix": false,
        "postfix": false,
        "binop": null,
        "updateContext": null
      },
      "value": "https://fonts.googleapis.com/css2?family=Cardo&family=Lato:wght@100;300;400&display=swap",
      "start": 934,
      "end": 1024,
      "loc": {
        "start": {
          "line": 21,
          "column": 15
        },
        "end": {
          "line": 21,
          "column": 105
        }
      }
    },
    {
      "type": {
        "label": ";",
        "beforeExpr": true,
        "startsExpr": false,
        "rightAssociative": false,
        "isLoop": false,
        "isAssign": false,
        "prefix": false,
        "postfix": false,
        "binop": null,
        "updateContext": null
      },
      "start": 1024,
      "end": 1025,
      "loc": {
        "start": {
          "line": 21,
          "column": 105
        },
        "end": {
          "line": 21,
          "column": 106
        }
      }
    },
    {
      "type": {
        "label": "}",
        "beforeExpr": false,
        "startsExpr": false,
        "rightAssociative": false,
        "isLoop": false,
        "isAssign": false,
        "prefix": false,
        "postfix": false,
        "binop": null
      },
      "start": 1032,
      "end": 1033,
      "loc": {
        "start": {
          "line": 22,
          "column": 6
        },
        "end": {
          "line": 22,
          "column": 7
        }
      }
    },
    {
      "type": {
        "label": "name",
        "beforeExpr": false,
        "startsExpr": true,
        "rightAssociative": false,
        "isLoop": false,
        "isAssign": false,
        "prefix": false,
        "postfix": false,
        "binop": null
      },
      "value": "static",
      "start": 1040,
      "end": 1046,
      "loc": {
        "start": {
          "line": 23,
          "column": 6
        },
        "end": {
          "line": 23,
          "column": 12
        }
      }
    },
    {
      "type": {
        "label": "name",
        "beforeExpr": false,
        "startsExpr": true,
        "rightAssociative": false,
        "isLoop": false,
        "isAssign": false,
        "prefix": false,
        "postfix": false,
        "binop": null
      },
      "value": "get",
      "start": 1047,
      "end": 1050,
      "loc": {
        "start": {
          "line": 23,
          "column": 13
        },
        "end": {
          "line": 23,
          "column": 16
        }
      }
    },
    {
      "type": {
        "label": "name",
        "beforeExpr": false,
        "startsExpr": true,
        "rightAssociative": false,
        "isLoop": false,
        "isAssign": false,
        "prefix": false,
        "postfix": false,
        "binop": null
      },
      "value": "ArrowEmail",
      "start": 1051,
      "end": 1061,
      "loc": {
        "start": {
          "line": 23,
          "column": 17
        },
        "end": {
          "line": 23,
          "column": 27
        }
      }
    },
    {
      "type": {
        "label": "(",
        "beforeExpr": true,
        "startsExpr": true,
        "rightAssociative": false,
        "isLoop": false,
        "isAssign": false,
        "prefix": false,
        "postfix": false,
        "binop": null
      },
      "start": 1061,
      "end": 1062,
      "loc": {
        "start": {
          "line": 23,
          "column": 27
        },
        "end": {
          "line": 23,
          "column": 28
        }
      }
    },
    {
      "type": {
        "label": ")",
        "beforeExpr": false,
        "startsExpr": false,
        "rightAssociative": false,
        "isLoop": false,
        "isAssign": false,
        "prefix": false,
        "postfix": false,
        "binop": null
      },
      "start": 1062,
      "end": 1063,
      "loc": {
        "start": {
          "line": 23,
          "column": 28
        },
        "end": {
          "line": 23,
          "column": 29
        }
      }
    },
    {
      "type": {
        "label": "{",
        "beforeExpr": true,
        "startsExpr": true,
        "rightAssociative": false,
        "isLoop": false,
        "isAssign": false,
        "prefix": false,
        "postfix": false,
        "binop": null
      },
      "start": 1064,
      "end": 1065,
      "loc": {
        "start": {
          "line": 23,
          "column": 30
        },
        "end": {
          "line": 23,
          "column": 31
        }
      }
    },
    {
      "type": {
        "label": "return",
        "keyword": "return",
        "beforeExpr": true,
        "startsExpr": false,
        "rightAssociative": false,
        "isLoop": false,
        "isAssign": false,
        "prefix": false,
        "postfix": false,
        "binop": null,
        "updateContext": null
      },
      "value": "return",
      "start": 1074,
      "end": 1080,
      "loc": {
        "start": {
          "line": 24,
          "column": 8
        },
        "end": {
          "line": 24,
          "column": 14
        }
      }
    },
    {
      "type": {
        "label": "string",
        "beforeExpr": false,
        "startsExpr": true,
        "rightAssociative": false,
        "isLoop": false,
        "isAssign": false,
        "prefix": false,
        "postfix": false,
        "binop": null,
        "updateContext": null
      },
      "value": "https://cdn.discordapp.com/attachments/973237631959855234/1121759694952857610/Clip_path_group.png",
      "start": 1081,
      "end": 1180,
      "loc": {
        "start": {
          "line": 24,
          "column": 15
        },
        "end": {
          "line": 24,
          "column": 114
        }
      }
    },
    {
      "type": {
        "label": ";",
        "beforeExpr": true,
        "startsExpr": false,
        "rightAssociative": false,
        "isLoop": false,
        "isAssign": false,
        "prefix": false,
        "postfix": false,
        "binop": null,
        "updateContext": null
      },
      "start": 1180,
      "end": 1181,
      "loc": {
        "start": {
          "line": 24,
          "column": 114
        },
        "end": {
          "line": 24,
          "column": 115
        }
      }
    },
    {
      "type": {
        "label": "}",
        "beforeExpr": false,
        "startsExpr": false,
        "rightAssociative": false,
        "isLoop": false,
        "isAssign": false,
        "prefix": false,
        "postfix": false,
        "binop": null
      },
      "start": 1188,
      "end": 1189,
      "loc": {
        "start": {
          "line": 25,
          "column": 6
        },
        "end": {
          "line": 25,
          "column": 7
        }
      }
    },
    {
      "type": {
        "label": "}",
        "beforeExpr": false,
        "startsExpr": false,
        "rightAssociative": false,
        "isLoop": false,
        "isAssign": false,
        "prefix": false,
        "postfix": false,
        "binop": null
      },
      "start": 1190,
      "end": 1191,
      "loc": {
        "start": {
          "line": 26,
          "column": 0
        },
        "end": {
          "line": 26,
          "column": 1
        }
      }
    },
    {
      "type": {
        "label": "export",
        "keyword": "export",
        "beforeExpr": false,
        "startsExpr": false,
        "rightAssociative": false,
        "isLoop": false,
        "isAssign": false,
        "prefix": false,
        "postfix": false,
        "binop": null,
        "updateContext": null
      },
      "value": "export",
      "start": 1194,
      "end": 1200,
      "loc": {
        "start": {
          "line": 29,
          "column": 0
        },
        "end": {
          "line": 29,
          "column": 6
        }
      }
    },
    {
      "type": {
        "label": "default",
        "keyword": "default",
        "beforeExpr": true,
        "startsExpr": false,
        "rightAssociative": false,
        "isLoop": false,
        "isAssign": false,
        "prefix": false,
        "postfix": false,
        "binop": null,
        "updateContext": null
      },
      "value": "default",
      "start": 1201,
      "end": 1208,
      "loc": {
        "start": {
          "line": 29,
          "column": 7
        },
        "end": {
          "line": 29,
          "column": 14
        }
      }
    },
    {
      "type": {
        "label": "name",
        "beforeExpr": false,
        "startsExpr": true,
        "rightAssociative": false,
        "isLoop": false,
        "isAssign": false,
        "prefix": false,
        "postfix": false,
        "binop": null
      },
      "value": "Constants",
      "start": 1209,
      "end": 1218,
      "loc": {
        "start": {
          "line": 29,
          "column": 15
        },
        "end": {
          "line": 29,
          "column": 24
        }
      }
    },
    {
      "type": {
        "label": ";",
        "beforeExpr": true,
        "startsExpr": false,
        "rightAssociative": false,
        "isLoop": false,
        "isAssign": false,
        "prefix": false,
        "postfix": false,
        "binop": null,
        "updateContext": null
      },
      "start": 1218,
      "end": 1219,
      "loc": {
        "start": {
          "line": 29,
          "column": 24
        },
        "end": {
          "line": 29,
          "column": 25
        }
      }
    },
    {
      "type": {
        "label": "eof",
        "beforeExpr": false,
        "startsExpr": false,
        "rightAssociative": false,
        "isLoop": false,
        "isAssign": false,
        "prefix": false,
        "postfix": false,
        "binop": null,
        "updateContext": null
      },
      "start": 1219,
      "end": 1219,
      "loc": {
        "start": {
          "line": 29,
          "column": 25
        },
        "end": {
          "line": 29,
          "column": 25
        }
      }
    }
  ]
}